jawadb.py
jawadb-0.3.0.dist-info/METADATA
jawadb-0.3.0.dist-info/WHEEL
jawadb-0.3.0.dist-info/licenses/LICENSE.txt
jawadb-0.3.0.dist-info/RECORD
