Metadata-Version: 2.4
Name: jawadb
Version: 0.3.0
Summary: A simple persistent JSON database for Python
Project-URL: Homepage, https://github.com/yourusername/jawadb
Project-URL: Repository, https://github.com/yourusername/jawadb.git
Author-email: Yoav Shai <gergesh@gmail.com>
License: MIT
License-File: LICENSE.txt
Classifier: Development Status :: 3 - Alpha
Classifier: Intended Audience :: Developers
Classifier: License :: OSI Approved :: MIT License
Classifier: Programming Language :: Python :: 3
Classifier: Programming Language :: Python :: 3.7
Classifier: Programming Language :: Python :: 3.8
Classifier: Programming Language :: Python :: 3.9
Classifier: Programming Language :: Python :: 3.10
Classifier: Programming Language :: Python :: 3.11
Requires-Python: >=3.7
